LICENSE
README.md
src/nzshm_rupture_widget/__init__.py
src/nzshm_rupture_widget/static/CesiumWidget.js
src/nzshm_rupture_widget/static/FullScreenWidget.js
src/nzshm_rupture_widget/static/HomeWidget.js
src/nzshm_rupture_widget/static/SliderWidget.js
src/nzshm_rupture_widget/static/ValueButtonWidget.js
src/nzshm_rupture_widget/static/widget.css
nzshm_rupture_widget-0.0.0.1.dist-info/METADATA
nzshm_rupture_widget-0.0.0.1.dist-info/WHEEL
nzshm_rupture_widget-0.0.0.1.dist-info/licenses/LICENSE
nzshm_rupture_widget-0.0.0.1.dist-info/RECORD
