Metadata-Version: 2.3
Name: nzshm_rupture_widget
Version: 0.0.0.1
Summary: Ipywidgets map widget that can display 3D GeoJSON.
Project-URL: Homepage, https://github.com/GNS-Science/nzshm-rupture-widget
Author-email: Oakley Jurgens <oakley.jurgens@gmail.com>
License: GPL3
License-File: LICENSE
Requires-Dist: anywidget
Provides-Extra: dev
Requires-Dist: jupyterlab; extra == 'dev'
Requires-Dist: watchfiles; extra == 'dev'
